cement_complete_fig/__init__.py
cement_complete_fig/fig.py
cement_complete_fig/ext/__init__.py
cement_complete_fig/ext/ext_complete_fig.py
cement_complete_fig-1.0.0.dist-info/LICENSE
cement_complete_fig-1.0.0.dist-info/METADATA
cement_complete_fig-1.0.0.dist-info/WHEEL
cement_complete_fig-1.0.0.dist-info/top_level.txt
cement_complete_fig-1.0.0.dist-info/RECORD
