Metadata-Version: 2.1
Name: cement-complete-fig
Version: 1.0.0
Summary: Autogenerate completions for CLI tools built with cement
Author-email: Fig Team <hello@fig.io>
Maintainer-email: Sean Sullivan <sean@fig.io>
License: MIT
Project-URL: Bug Tracker, https://github.com/withfig/autocomplete-tools/issues
Project-URL: Homepage, https://github.com/withfig/autocomplete-tools
Keywords: cement,fig,cli,completions,terminal,framework
Classifier: Programming Language :: Python :: 3
Classifier: License :: OSI Approved :: MIT License
Classifier: Operating System :: OS Independent
Requires-Python: >=3.5
License-File: LICENSE
Requires-Dist: argparse-complete-fig
Requires-Dist: cement
